charz/__init__.py
charz/_animation.py
charz/_annotations.py
charz/_asset_loader.py
charz/_clock.py
charz/_engine.py
charz/_grouping.py
charz/_non_negative.py
charz/_scene_tasks.py
charz/_screen.py
charz/_time.py
charz/py.typed
charz/text.py
charz/_components/_animated.py
charz/_components/_collision.py
charz/_components/_color.py
charz/_components/_simple_movement.py
charz/_components/_texture.py
charz/_prefabs/_animated_sprite.py
charz/_prefabs/_label.py
charz/_prefabs/_sprite.py
charz-0.1.1.dist-info/METADATA
charz-0.1.1.dist-info/WHEEL
charz-0.1.1.dist-info/licenses/LICENSE
charz-0.1.1.dist-info/RECORD
