Metadata-Version: 2.3
Name: charz
Version: 0.1.1
Summary: An object oriented terminal game engine
Author-email: Havsalt <77575424+Havsalt@users.noreply.github.com>
License: MIT License
Classifier: Development Status :: 4 - Beta
Classifier: Environment :: Console
Classifier: Intended Audience :: Developers
Classifier: Natural Language :: English
Classifier: Operating System :: OS Independent
Classifier: Programming Language :: Python :: 3
Classifier: Programming Language :: Python :: 3 :: Only
Classifier: Programming Language :: Python :: 3.10
Classifier: Programming Language :: Python :: 3.11
Classifier: Programming Language :: Python :: 3.12
Classifier: Programming Language :: Python :: 3.13
Classifier: Programming Language :: Python :: Implementation :: CPython
Classifier: Programming Language :: Python :: Implementation :: PyPy
Classifier: Topic :: Games/Entertainment
Classifier: Topic :: Software Development
Classifier: Topic :: Utilities
Classifier: Typing :: Typed
Requires-Python: >=3.10
Requires-Dist: charz-core~=0.1.0
Requires-Dist: colex~=0.3.0
Provides-Extra: all
Requires-Dist: keyboard>=0.13.5; extra == 'all'
Provides-Extra: keyboard
Requires-Dist: keyboard>=0.13.5; extra == 'keyboard'
